tmlt/private_pgm/__init__.py
tmlt/private_pgm/callbacks.py
tmlt/private_pgm/clique_vector.py
tmlt/private_pgm/dataset.py
tmlt/private_pgm/domain.py
tmlt/private_pgm/factor.py
tmlt/private_pgm/factor_graph.py
tmlt/private_pgm/graphical_model.py
tmlt/private_pgm/inference.py
tmlt/private_pgm/junction_tree.py
tmlt/private_pgm/local_inference.py
tmlt/private_pgm/mechanism.py
tmlt/private_pgm/public_inference.py
tmlt/private_pgm/region_graph.py
tmlt_private_pgm-0.1.1a2.dist-info/LICENSE
tmlt_private_pgm-0.1.1a2.dist-info/METADATA
tmlt_private_pgm-0.1.1a2.dist-info/WHEEL
tmlt_private_pgm-0.1.1a2.dist-info/RECORD
