Metadata-Version: 2.1
Name: tmlt.private_pgm
Version: 0.1.1a2
Summary: Graphical-model based estimation and inference for differential privacy.
Home-page: https://gitlab.com/tumult-labs/private_pgm
License: Apache-2.0
Requires-Python: >=3.8.0,<3.13
Classifier: License :: OSI Approved :: Apache Software License
Classifier: Programming Language :: Python :: 3
Classifier: Programming Language :: Python :: 3.8
Classifier: Programming Language :: Python :: 3.9
Classifier: Programming Language :: Python :: 3.10
Classifier: Programming Language :: Python :: 3.11
Classifier: Programming Language :: Python :: 3.12
Requires-Dist: networkx (==3.1)
Requires-Dist: numpy (>=1.22.0,<1.25.0) ; python_version >= "3.8" and python_version < "3.9"
Requires-Dist: numpy (>=1.23.2,<2.0.0) ; python_version >= "3.9" and python_version < "3.12"
Requires-Dist: numpy (>=1.26.0,<2.0.0) ; python_version >= "3.12"
Requires-Dist: pandas (>=1.4.0,<2.0.0) ; python_version >= "3.8" and python_version < "3.11"
Requires-Dist: pandas (>=1.5.0,<2.0.0) ; python_version >= "3.11" and python_version < "3.12"
Requires-Dist: pandas (>=2.2.0,<3.0.0) ; python_version >= "3.12"
Requires-Dist: scipy (>=1.11.2,<2.0.0) ; python_version >= "3.12"
Requires-Dist: scipy (>=1.6.0,<1.11.0) ; python_version >= "3.8" and python_version < "3.9"
Requires-Dist: scipy (>=1.6.0,<2.0.0) ; python_version >= "3.9" and python_version < "3.10"
Requires-Dist: scipy (>=1.8.0,<2.0.0) ; python_version >= "3.10" and python_version < "3.11"
Requires-Dist: scipy (>=1.9.2,<2.0.0) ; python_version >= "3.11" and python_version < "3.12"
Project-URL: Repository, https://gitlab.com/tumult-labs/private_pgm
